setup.py
clicrud/__init__.py
clicrud.egg-info/PKG-INFO
clicrud.egg-info/SOURCES.txt
clicrud.egg-info/dependency_links.txt
clicrud.egg-info/requires.txt
clicrud.egg-info/top_level.txt
clicrud/clicrud/__init__.py
clicrud/clicrud/helpers.py
clicrud/clicrud/multiprocess.py
clicrud/clicrud/setup.py
clicrud/clicrud/templatehelpers.py
clicrud/crud/__init__.py
clicrud/device/__init__.py
clicrud/device/generic/__init__.py
clicrud/device/generic/ver/__init__.py
clicrud/device/generic/ver/base/__init__.py
tests/__init__.py