Metadata-Version: 1.1
Name: clicrud
Version: 0.2.12
Summary: Brocade CLI CRUD Operations Library.
Home-page: http://www.brocade.com/
Author: Brocade Communications Systems, Inc.
Author-email: dgee@brocade.com
License: UNKNOWN
Platform: UNKNOWN
Classifier: Development Status :: 5 - Production/Stable
Classifier: Intended Audience :: Developers
Classifier: License :: OSI Approved :: Apache Software License
Classifier: Operating System :: OS Independent
Classifier: Programming Language :: Python
Classifier: Programming Language :: Python :: 2.7
Classifier: Topic :: Software Development :: Libraries
Classifier: Topic :: Software Development :: Libraries :: Python Modules
Classifier: Topic :: System :: Networking
